tableprint/__init__.py
tableprint/metadata.py
tableprint/printer.py
tableprint/style.py
tableprint/utils.py
tableprint-0.9.1.dist-info/METADATA
tableprint-0.9.1.dist-info/WHEEL
tableprint-0.9.1.dist-info/top_level.txt
tableprint-0.9.1.dist-info/RECORD
